compacter
